<?xml version="1.0" encoding="UTF-8"?>
<!DOCTYPE suite SYSTEM "https://testng.org/testng-1.0.dtd">
<suite name="Suite">
  <test thread-count="5" name="Test">
    <classes>
      <class name="tests.AuthenticationRegistrationPageTests">
      	<methods>
      		<exclude name="beforeClass"></exclude>
    		<exclude name="createNewAccount"></exclude>
      		<include name="logInUser"/>
      		<include name="logInExistingUser"/>
      		<include name="logInNonExistingUser"/>
      		<include name="logInWithWrongPassword"/>
      	</methods>
      </class>
    </classes>
  </test> <!-- Test -->
</suite> <!-- Suite -->
